scavenger.py
csv_scavenger-1.0.5.dist-info/LICENSE
csv_scavenger-1.0.5.dist-info/METADATA
csv_scavenger-1.0.5.dist-info/WHEEL
csv_scavenger-1.0.5.dist-info/RECORD
