Metadata-Version: 2.1
Name: csv-scavenger
Version: 1.0.5
Summary: CSV reader and parser with automatic detection of delimiter and start/end of data.
Author: Gustave Coulombe
Author-email: magikgus@gmail.com
Requires-Python: >=3.11,<3.12
Classifier: Programming Language :: Python :: 3
Classifier: Programming Language :: Python :: 3.11
Requires-Dist: pandas (>=2.0.0,<3.0.0)
Requires-Dist: tssplit (>=1.0.6,<2.0.0)
